LICENSE.txt
MANIFEST.in
README.md
setup.py
jk_tokenizingparsing/AbstractTextConverter.py
jk_tokenizingparsing/CompiledTokenizer.py
jk_tokenizingparsing/Convert4HexToUnicode.py
jk_tokenizingparsing/JSONLoader.py
jk_tokenizingparsing/ParserBase.py
jk_tokenizingparsing/ParserErrorException.py
jk_tokenizingparsing/ParsingContext.py
jk_tokenizingparsing/Serializer.py
jk_tokenizingparsing/SourceCodeLocation.py
jk_tokenizingparsing/TextBuffer.py
jk_tokenizingparsing/TextConverterManager.py
jk_tokenizingparsing/Token.py
jk_tokenizingparsing/TokenStream.py
jk_tokenizingparsing/TokenStreamMark.py
jk_tokenizingparsing/TokenizerAction.py
jk_tokenizingparsing/TokenizerBase.py
jk_tokenizingparsing/TokenizerPattern.py
jk_tokenizingparsing/TokenizingTable.py
jk_tokenizingparsing/_PatternTableRecord.py
jk_tokenizingparsing/_TokenizerActionTuple.py
jk_tokenizingparsing/_TokenizerPatternTuple.py
jk_tokenizingparsing/__init__.py
jk_tokenizingparsing.egg-info/PKG-INFO
jk_tokenizingparsing.egg-info/SOURCES.txt
jk_tokenizingparsing.egg-info/dependency_links.txt
jk_tokenizingparsing.egg-info/not-zip-safe
jk_tokenizingparsing.egg-info/top_level.txt
jk_tokenizingparsing/tokenmatching/AbstractTokenPattern.py
jk_tokenizingparsing/tokenmatching/MatchResult.py
jk_tokenizingparsing/tokenmatching/TP.py
jk_tokenizingparsing/tokenmatching/TPAlt.py
jk_tokenizingparsing/tokenmatching/TPAny.py
jk_tokenizingparsing/tokenmatching/TPOptional.py
jk_tokenizingparsing/tokenmatching/TPRepeat.py
jk_tokenizingparsing/tokenmatching/TPSeq.py
jk_tokenizingparsing/tokenmatching/TPUnordSeq.py
jk_tokenizingparsing/tokenmatching/_Triplet.py
jk_tokenizingparsing/tokenmatching/__init__.py