Metadata-Version: 2.1
Name: jk-tokenizingparsing
Version: 0.2020.1.20
Summary: This python module provides basic classes for tokenizing and parsing.
Home-page: https://github.com/jkpubsrc/python-module-jk-tokenizingparsing
Author: Jürgen Knauth
Author-email: pubsrc@binary-overflow.de
License: Apache 2.0
Download-URL: https://github.com/jkpubsrc/python-module-jk-tokenizingparsing/tarball/0.2020.1.20
Keywords: tokenizing,parsing
Platform: UNKNOWN
Classifier: Development Status :: 4 - Beta
Classifier: License :: OSI Approved :: Apache Software License
